README.md
setup.py
nmp/__init__.py
nmp/cli.py
nmp/model_logic_extractor.py
nmp.egg-info/PKG-INFO
nmp.egg-info/SOURCES.txt
nmp.egg-info/dependency_links.txt
nmp.egg-info/entry_points.txt
nmp.egg-info/requires.txt
nmp.egg-info/top_level.txt