Metadata-Version: 1.0
Name: nmp
Version: 3
Summary: Notebook Model Packager for Vertex AI
Home-page: http://pypi.python.org/pypi/nmp/
Author: Viacheslav Kovalevskyi
Author-email: viacheslav@kovalevskyi.com
License: LICENSE
Platform: UNKNOWN
